eaton_ups_companion/__init__.py
eaton_ups_companion/eucclient.py
eaton_ups_companion/models/__init__.py
eaton_ups_companion/models/deviceinfo.py
eaton_ups_companion/models/ecocontrol.py
eaton_ups_companion/models/eucresponse.py
eaton_ups_companion/models/logentry.py
eaton_ups_companion/models/logs.py
eaton_ups_companion/models/powersourcecfg.py
eaton_ups_companion/models/shutdowncfg.py
eaton_ups_companion/models/status.py
eaton_ups_companion/models/sysinfo.py
eaton_ups_companion/models/systemcfg.py
eaton_ups_companion/models/voltagerange.py
eaton_ups_companion-2025.4.0.dist-info/licenses/LICENSE
eaton_ups_companion-2025.4.0.dist-info/METADATA
eaton_ups_companion-2025.4.0.dist-info/WHEEL
eaton_ups_companion-2025.4.0.dist-info/top_level.txt
eaton_ups_companion-2025.4.0.dist-info/RECORD
