Metadata-Version: 2.4
Name: eaton-ups-companion
Version: 2025.4.0
Summary: Asynchronous Python library for Eaton UPS Companion API
Author-email: Jimmy Everling <jimmy@sockless.tech>
License: MIT License
Project-URL: Homepage, https://github.com/sockless-coding/eaton-ups-companion
Project-URL: Repository, https://github.com/sockless-coding/eaton-ups-companion.git
Project-URL: Bug Tracker, https://github.com/sockless-coding/eaton-ups-companion/issues
Keywords: eaton,ups companion,ups
Classifier: Programming Language :: Python :: 3
Classifier: License :: OSI Approved :: MIT License
Classifier: Operating System :: OS Independent
Requires-Python: >=3.10
License-File: LICENSE
Requires-Dist: aiohttp
Dynamic: license-file
